streamingpool/FIFOPool.py
streamingpool/LIFOPool.py
streamingpool/__init__.py
streamingpool/abstraction/__init__.py
streamingpool/abstraction/basePool.py
streamingpool/genericity/__init__.py
streamingpool/genericity/t_segment.py
streamingpool/models/__init__.py
streamingpool/models/discard.py
streamingpool-1.1.2.dist-info/LICENSE
streamingpool-1.1.2.dist-info/METADATA
streamingpool-1.1.2.dist-info/WHEEL
streamingpool-1.1.2.dist-info/top_level.txt
streamingpool-1.1.2.dist-info/RECORD
