Metadata-Version: 2.1
Name: streamingpool
Version: 1.1.2
Home-page: https://github.com/Neyzv/StreamingPool
Author: Neyzu
License-File: LICENSE
